{"id": "9f5805a4-3d80-48d2-99eb-838f7e68f1c5", "type": "commit-range", "scans": [{"id": "1dbd1697526a0352c664d787a6c5146e844c7094", "type": "commit", "entities_with_incidents": [{"mode": "MODIFY", "filename": ".github/workflows/automatic-release.yml", "incidents": [], "total_incidents": 0, "total_occurrences": 0}, {"mode": "MODIFY", "filename": "scripts/manual-release.sh", "incidents": [], "total_incidents": 0, "total_occurrences": 0}], "extra_info": {"author": "Karl Bauer", "email": "karl.bauer@bauer-group.com", "date": "Tue Aug 19 17:36:13 2025 +0200"}, "total_incidents": 0, "total_occurrences": 0}, {"id": "1fca53fc4d75913ed83ac76431d94a812e3f0c42", "type": "commit", "entities_with_incidents": [{"mode": "MODIFY", "filename": "README.MD", "incidents": [], "total_incidents": 0, "total_occurrences": 0}], "extra_info": {"author": "\ud83d\udcc4 README Generator", "email": "action@github.com", "date": "Tue Aug 19 15:36:50 2025 +0000"}, "total_incidents": 0, "total_occurrences": 0}], "total_incidents": 0, "total_occurrences": 0, "secrets_engine_version": "2.145.0"}